cli_pdf_viewer-0.0.1.data/scripts/pdfviewer.py
src/__init__.py
src/pdfviewer.py
cli_pdf_viewer-0.0.1.dist-info/METADATA
cli_pdf_viewer-0.0.1.dist-info/WHEEL
cli_pdf_viewer-0.0.1.dist-info/entry_points.txt
cli_pdf_viewer-0.0.1.dist-info/top_level.txt
cli_pdf_viewer-0.0.1.dist-info/RECORD
